Metadata-Version: 1.0
Name: Algorithme
Version: 0.1
Summary: simple project
Home-page: UNKNOWN
Author: Mohamed Chaabi
Author-email: mohaachch@gmail.com
License: MIT
Platform: UNKNOWN
